arcadb/__init__.py
arcadb/base.py
arcadb/imports.py
arcadb/tools.py
arcadb-0.1.1.dist-info/LICENSE
arcadb-0.1.1.dist-info/METADATA
arcadb-0.1.1.dist-info/WHEEL
arcadb-0.1.1.dist-info/top_level.txt
arcadb-0.1.1.dist-info/RECORD
